[
    {
        "title": "Sousou no Frieren",
        "rating": 9.31
    },
    {
        "title": "Fullmetal Alchemist: Brotherhood",
        "rating": 9.1
    },
    {
        "title": "Steins;Gate",
        "rating": 9.07
    },
    {
        "title": "One Piece Fan Letter",
        "rating": 9.06
    },
    {
        "title": "Shingeki no Kyojin Season 3 Part 2",
        "rating": 9.05
    },
    {
        "title": "Gintama°",
        "rating": 9.05
    },
    {
        "title": "Gintama: The Final",
        "rating": 9.04
    },
    {
        "title": "Hunter x Hunter (2011)",
        "rating": 9.03
    },
    {
        "title": "Gintama'",
        "rating": 9.02
    },
    {
        "title": "Gintama': Enchousen",
        "rating": 9.02
    },
    {
        "title": "Ginga Eiyuu Densetsu",
        "rating": 9.01
    },
    {
        "title": "Bleach: Sennen Kessen-hen",
        "rating": 9
    },
    {
        "title": "Kaguya-sama wa Kokurasetai: Ultra Romantic",
        "rating": 8.99
    },
    {
        "title": "Gintama.",
        "rating": 8.98
    },
    {
        "title": "Fruits Basket: The Final",
        "rating": 8.96
    },
    {
        "title": "Clannad: After Story",
        "rating": 8.93
    },
    {
        "title": "Gintama",
        "rating": 8.93
    },
    {
        "title": "Koe no Katachi",
        "rating": 8.93
    },
    {
        "title": "3-gatsu no Lion 2nd Season",
        "rating": 8.91
    },
    {
        "title": "Code Geass: Hangyaku no Lelouch R2",
        "rating": 8.91
    },
    {
        "title": "Gintama Movie 2: Kanketsu-hen - Yorozuya yo Eien Nare",
        "rating": 8.9
    },
    {
        "title": "Kusuriya no Hitorigoto",
        "rating": 8.88
    },
    {
        "title": "Gintama. Shirogane no Tamashii-hen - Kouhan-sen",
        "rating": 8.88
    },
    {
        "title": "Monster",
        "rating": 8.88
    },
    {
        "title": "Shingeki no Kyojin: The Final Season - Kanketsu-hen",
        "rating": 8.87
    }
]